sendiniran/__init__.py
sendiniran/main.py
sendiniran-0.1.2.dist-info/METADATA
sendiniran-0.1.2.dist-info/WHEEL
sendiniran-0.1.2.dist-info/top_level.txt
sendiniran-0.1.2.dist-info/RECORD
